qdts_client/interfaces_pb2.py
qdts_client/interfaces_pb2_grpc.py
qdts_client/qdts_etsi_004_client.py
qdts_client-0.2.0.dist-info/METADATA
qdts_client-0.2.0.dist-info/WHEEL
qdts_client-0.2.0.dist-info/RECORD
